[
	{
		"nome": "Kauê Alexandre de Paula",
		"idade": 18,
		"cpf": "94172028390",
		"rg": "456051478",
		"data_nasc": "22\/06\/2003",
		"sexo": "Masculino",
		"signo": "Câncer",
		"mae": "Tânia Patrícia",
		"pai": "Kauê Carlos Eduardo José de Paula",
		"email": "kkauealexandredepaula@gamil.com",
		"senha": "18t8s7E6zZ",
		"cep": "72853411",
		"endereco": "Quadra Quadra 411",
		"numero": 923,
		"bairro": "Parque Estrela Dalva IX",
		"cidade": "Luziânia",
		"estado": "GO",
		"telefone_fixo": "6129836929",
		"celular": "61991780802",
		"altura": "1,70",
		"peso": 63,
		"tipo_sanguineo": "A-",
		"cor": "laranja"
	},
	{
		"nome": "Yuri Ruan da Conceição",
		"idade": 31,
		"cpf": "76244335597",
		"rg": "211631048",
		"data_nasc": "08\/09\/1990",
		"sexo": "Masculino",
		"signo": "Virgem",
		"mae": "Catarina Beatriz Patrícia",
		"pai": "Alexandre Tiago Jorge da Conceição",
		"email": "yuriruandaconceicao__yuriruandaconceicao@yahool.com.br",
		"senha": "yk1YyWsAjA",
		"cep": "79040560",
		"endereco": "Rua José Maria Hugo Rodrigues",
		"numero": 966,
		"bairro": "Chácara Cachoeira",
		"cidade": "Campo Grande",
		"estado": "MS",
		"telefone_fixo": "6736189209",
		"celular": "67982278523",
		"altura": "1,64",
		"peso": 97,
		"tipo_sanguineo": "O-",
		"cor": "vermelho"
	},
	{
		"nome": "Samuel Marcos Cláudio Fernandes",
		"idade": 68,
		"cpf": "00737689951",
		"rg": "365668291",
		"data_nasc": "24\/05\/1953",
		"sexo": "Masculino",
		"signo": "Gêmeos",
		"mae": "Stefany Olivia Betina",
		"pai": "Fábio Ricardo Fernandes",
		"email": "samuelmarcosclaudiofernandes..samuelmarcosclaudiofernandes@gmail.com",
		"senha": "lCEYWzBMy9",
		"cep": "35660306",
		"endereco": "Rua Paris",
		"numero": 442,
		"bairro": "Jardim Serra Dourada",
		"cidade": "Pará de Minas",
		"estado": "MG",
		"telefone_fixo": "3728377658",
		"celular": "37992580090",
		"altura": "1,61",
		"peso": 57,
		"tipo_sanguineo": "O-",
		"cor": "preto"
	},
	{
		"nome": "Giovanna Laís Andrea da Mota",
		"idade": 26,
		"cpf": "34482482587",
		"rg": "292446032",
		"data_nasc": "06\/06\/1995",
		"sexo": "Feminino",
		"signo": "Gêmeos",
		"mae": "Simone Nina",
		"pai": "Leandro Bryan da Mota",
		"email": "giovannalaisandreadamota__giovannalaisandreadamota@liv.com",
		"senha": "uDwN3CsuPO",
		"cep": "69912320",
		"endereco": "Rua Artesanato",
		"numero": 648,
		"bairro": "Floresta Sul",
		"cidade": "Rio Branco",
		"estado": "AC",
		"telefone_fixo": "6829828667",
		"celular": "68994724473",
		"altura": "1,79",
		"peso": 65,
		"tipo_sanguineo": "A+",
		"cor": "preto"
	},
	{
		"nome": "Lara Isabelly Vitória Assunção",
		"idade": 76,
		"cpf": "51424971209",
		"rg": "292360666",
		"data_nasc": "26\/07\/1945",
		"sexo": "Feminino",
		"signo": "Leão",
		"mae": "Sophia Sandra Aparecida",
		"pai": "Levi Oliver Assunção",
		"email": "laraisabellyvitoriaassuncao_@iaru.com.br",
		"senha": "beq5tI3cTL",
		"cep": "72215330",
		"endereco": "Quadra QNM 33",
		"numero": 216,
		"bairro": "Ceilândia Sul (Ceilândia)",
		"cidade": "Brasília",
		"estado": "DF",
		"telefone_fixo": "6127836085",
		"celular": "61989818394",
		"altura": "1,71",
		"peso": 83,
		"tipo_sanguineo": "AB-",
		"cor": "azul"
	},
	{
		"nome": "Enzo Pedro Henrique Carlos Duarte",
		"idade": 54,
		"cpf": "28509439915",
		"rg": "434266541",
		"data_nasc": "16\/10\/1967",
		"sexo": "Masculino",
		"signo": "Libra",
		"mae": "Evelyn Olivia Agatha",
		"pai": "Juan Fernando Duarte",
		"email": "enzopedrohenriquecarlosduarte..enzopedrohenriquecarlosduarte@andritz.com",
		"senha": "uRdTWcytYw",
		"cep": "49900970",
		"endereco": "Rua Getulio Vargas 80",
		"numero": 247,
		"bairro": "Centro",
		"cidade": "Propriá",
		"estado": "SE",
		"telefone_fixo": "7938618560",
		"celular": "79984429106",
		"altura": "1,87",
		"peso": 95,
		"tipo_sanguineo": "B+",
		"cor": "roxo"
	},
	{
		"nome": "Analu Bárbara Barbosa",
		"idade": 55,
		"cpf": "83426346044",
		"rg": "323229566",
		"data_nasc": "02\/11\/1966",
		"sexo": "Feminino",
		"signo": "Escorpião",
		"mae": "Rayssa Rosa Regina",
		"pai": "Augusto Pedro Bento Barbosa",
		"email": "analubarbarabarbosa_@rcstechnology.com.br",
		"senha": "l05ARlBfjg",
		"cep": "74474129",
		"endereco": "Rua JH 23",
		"numero": 153,
		"bairro": "Jardim das Hortências",
		"cidade": "Goiânia",
		"estado": "GO",
		"telefone_fixo": "6225615917",
		"celular": "62997168152",
		"altura": "1,55",
		"peso": 80,
		"tipo_sanguineo": "B-",
		"cor": "roxo"
	},
	{
		"nome": "Julia Sophie Emily Melo",
		"idade": 55,
		"cpf": "84801716938",
		"rg": "434869259",
		"data_nasc": "10\/10\/1966",
		"sexo": "Feminino",
		"signo": "Libra",
		"mae": "Esther Giovanna Larissa",
		"pai": "Samuel Marcos Vinicius Nelson Melo",
		"email": "juliasophieemilymelo_@eletrovip.com",
		"senha": "wTglUnUhRU",
		"cep": "76829560",
		"endereco": "Rua Antônio Violão",
		"numero": 801,
		"bairro": "Tancredo Neves",
		"cidade": "Porto Velho",
		"estado": "RO",
		"telefone_fixo": "6939213308",
		"celular": "69999635640",
		"altura": "1,69",
		"peso": 49,
		"tipo_sanguineo": "A-",
		"cor": "verde"
	},
	{
		"nome": "Ayla Julia Stella Rodrigues",
		"idade": 71,
		"cpf": "29983457512",
		"rg": "219760408",
		"data_nasc": "03\/01\/1950",
		"sexo": "Feminino",
		"signo": "Capricórnio",
		"mae": "Lúcia Maria",
		"pai": "Gabriel Rodrigo Rodrigues",
		"email": "aaylajuliastellarodrigues@creativeinteriores.com.br",
		"senha": "4ehe0mkxEU",
		"cep": "78115080",
		"endereco": "Rua José Leite de Moraes",
		"numero": 389,
		"bairro": "Ponte Nova",
		"cidade": "Várzea Grande",
		"estado": "MT",
		"telefone_fixo": "6539436425",
		"celular": "65994504497",
		"altura": "1,57",
		"peso": 61,
		"tipo_sanguineo": "AB-",
		"cor": "verde"
	},
	{
		"nome": "Cecília Luna Betina da Rocha",
		"idade": 71,
		"cpf": "81231680474",
		"rg": "405969946",
		"data_nasc": "19\/03\/1950",
		"sexo": "Feminino",
		"signo": "Peixes",
		"mae": "Carla Rayssa Bianca",
		"pai": "Pietro Nathan da Rocha",
		"email": "ccecilialunabetinadarocha@petrobrais.com.br",
		"senha": "GsYWGiD6of",
		"cep": "60752400",
		"endereco": "Rua 10",
		"numero": 490,
		"bairro": "Mondubim",
		"cidade": "Fortaleza",
		"estado": "CE",
		"telefone_fixo": "8539261275",
		"celular": "85991759382",
		"altura": "1,61",
		"peso": 57,
		"tipo_sanguineo": "O-",
		"cor": "laranja"
	},
	{
		"nome": "Caroline Elisa Isabelle Dias",
		"idade": 74,
		"cpf": "41617646857",
		"rg": "323552742",
		"data_nasc": "07\/06\/1947",
		"sexo": "Feminino",
		"signo": "Gêmeos",
		"mae": "Regina Rosa Alice",
		"pai": "Benjamin Renato Bryan Dias",
		"email": "carolineelisaisabelledias..carolineelisaisabelledias@grupoprovac.com.br",
		"senha": "gErLNdzpGr",
		"cep": "69318754",
		"endereco": "Rua Governador José Maria Barbosa",
		"numero": 524,
		"bairro": "Dr. Airton Rocha",
		"cidade": "Boa Vista",
		"estado": "RR",
		"telefone_fixo": "9539444179",
		"celular": "95984173965",
		"altura": "1,57",
		"peso": 86,
		"tipo_sanguineo": "A-",
		"cor": "vermelho"
	},
	{
		"nome": "Leonardo Gael Fogaça",
		"idade": 40,
		"cpf": "54472769263",
		"rg": "179999618",
		"data_nasc": "05\/06\/1981",
		"sexo": "Masculino",
		"signo": "Gêmeos",
		"mae": "Sônia Emanuelly Evelyn",
		"pai": "Daniel Sérgio Kevin Fogaça",
		"email": "leonardogaelfogaca_@teravida.com.br",
		"senha": "BlRcThM9cc",
		"cep": "65083324",
		"endereco": "Rua União",
		"numero": 304,
		"bairro": "Cidade Nova",
		"cidade": "São Luís",
		"estado": "MA",
		"telefone_fixo": "9826959109",
		"celular": "98989743007",
		"altura": "1,79",
		"peso": 86,
		"tipo_sanguineo": "AB+",
		"cor": "roxo"
	},
	{
		"nome": "Natália Mirella Fernandes",
		"idade": 55,
		"cpf": "50424734591",
		"rg": "230508364",
		"data_nasc": "02\/04\/1966",
		"sexo": "Feminino",
		"signo": "Áries",
		"mae": "Teresinha Carolina Lúcia",
		"pai": "Renato Sebastião Samuel Fernandes",
		"email": "nataliamirellafernandes..nataliamirellafernandes@live.dk",
		"senha": "nGWDZwzrMW",
		"cep": "76913822",
		"endereco": "Avenida Édson Lima do Nascimento",
		"numero": 437,
		"bairro": "Jardim São Cristóvão",
		"cidade": "Ji-Paraná",
		"estado": "RO",
		"telefone_fixo": "6929384538",
		"celular": "69981786153",
		"altura": "1,76",
		"peso": 76,
		"tipo_sanguineo": "O+",
		"cor": "azul"
	},
	{
		"nome": "Fernanda Giovana Araújo",
		"idade": 18,
		"cpf": "67943107756",
		"rg": "150548138",
		"data_nasc": "21\/11\/2003",
		"sexo": "Feminino",
		"signo": "Escorpião",
		"mae": "Fernanda Lorena Kamilly",
		"pai": "Mateus Filipe Breno Araújo",
		"email": "fernandagiovanaaraujo-75@tilapiareal.com.br",
		"senha": "dHtZmGgnyQ",
		"cep": "59054725",
		"endereco": "Avenida Antônio Basílio",
		"numero": 846,
		"bairro": "Lagoa Nova",
		"cidade": "Natal",
		"estado": "RN",
		"telefone_fixo": "8436093311",
		"celular": "84998992249",
		"altura": "1,69",
		"peso": 58,
		"tipo_sanguineo": "B+",
		"cor": "vermelho"
	},
	{
		"nome": "Cecília Eloá Bruna Assunção",
		"idade": 64,
		"cpf": "09609934870",
		"rg": "425746306",
		"data_nasc": "16\/10\/1957",
		"sexo": "Feminino",
		"signo": "Libra",
		"mae": "Elaine Aparecida",
		"pai": "Jorge Guilherme Assunção",
		"email": "cceciliaeloabrunaassuncao@consultoriosjc.com.br",
		"senha": "ba1HcyCxP6",
		"cep": "80050255",
		"endereco": "Avenida Sete de Setembro",
		"numero": 273,
		"bairro": "Cristo Rei",
		"cidade": "Curitiba",
		"estado": "PR",
		"telefone_fixo": "4138850640",
		"celular": "41991848538",
		"altura": "1,51",
		"peso": 85,
		"tipo_sanguineo": "O+",
		"cor": "laranja"
	},
	{
		"nome": "Laura Stefany Alícia Pires",
		"idade": 71,
		"cpf": "63348192080",
		"rg": "256889168",
		"data_nasc": "19\/04\/1950",
		"sexo": "Feminino",
		"signo": "Áries",
		"mae": "Alícia Elza",
		"pai": "Daniel Samuel Leonardo Pires",
		"email": "laurastefanyaliciapires__laurastefanyaliciapires@cassianoricardo.com.br",
		"senha": "d6fzWXARmD",
		"cep": "64055909",
		"endereco": "Rua Professor Bartolomeu Filho 4833",
		"numero": 236,
		"bairro": "Santa Isabel",
		"cidade": "Teresina",
		"estado": "PI",
		"telefone_fixo": "8637994580",
		"celular": "86988386231",
		"altura": "1,66",
		"peso": 68,
		"tipo_sanguineo": "A-",
		"cor": "vermelho"
	},
	{
		"nome": "Eloá Jennifer Daniela Ramos",
		"idade": 43,
		"cpf": "32360093142",
		"rg": "263166533",
		"data_nasc": "05\/10\/1978",
		"sexo": "Feminino",
		"signo": "Libra",
		"mae": "Sebastiana Marcela",
		"pai": "Kaique Carlos Eduardo Ramos",
		"email": "eloajenniferdanielaramos..eloajenniferdanielaramos@yaooh.com",
		"senha": "LHBfzDgtbp",
		"cep": "60831413",
		"endereco": "Rua Jorge Sosa",
		"numero": 706,
		"bairro": "Lagoa Redonda",
		"cidade": "Fortaleza",
		"estado": "CE",
		"telefone_fixo": "8526963692",
		"celular": "85995958687",
		"altura": "1,83",
		"peso": 56,
		"tipo_sanguineo": "B-",
		"cor": "verde"
	},
	{
		"nome": "Raquel Mirella Drumond",
		"idade": 43,
		"cpf": "28424392108",
		"rg": "169776207",
		"data_nasc": "10\/06\/1978",
		"sexo": "Feminino",
		"signo": "Gêmeos",
		"mae": "Luana Tatiane Eliane",
		"pai": "Fernando Manuel Enrico Drumond",
		"email": "rraquelmirelladrumond@domain.com.br",
		"senha": "Rd1YkQfMeq",
		"cep": "69901510",
		"endereco": "Estrada São do Francisco",
		"numero": 213,
		"bairro": "São Francisco",
		"cidade": "Rio Branco",
		"estado": "AC",
		"telefone_fixo": "6825585115",
		"celular": "68983531955",
		"altura": "1,51",
		"peso": 88,
		"tipo_sanguineo": "A-",
		"cor": "verde"
	},
	{
		"nome": "Iago Julio Galvão",
		"idade": 25,
		"cpf": "39860826110",
		"rg": "395095517",
		"data_nasc": "19\/02\/1996",
		"sexo": "Masculino",
		"signo": "Aquário",
		"mae": "Gabriela Analu Maria",
		"pai": "Hugo Calebe Galvão",
		"email": "iagojuliogalvao-81@bol.br",
		"senha": "lE2ft6X9kh",
		"cep": "88508170",
		"endereco": "Rua Lourenço Teodoro Waltrick",
		"numero": 798,
		"bairro": "Sagrado Coração de Jesus",
		"cidade": "Lages",
		"estado": "SC",
		"telefone_fixo": "4927278700",
		"celular": "49987342279",
		"altura": "1,70",
		"peso": 101,
		"tipo_sanguineo": "A+",
		"cor": "vermelho"
	},
	{
		"nome": "Analu Rebeca Benedita Caldeira",
		"idade": 27,
		"cpf": "42787904904",
		"rg": "375228238",
		"data_nasc": "22\/05\/1994",
		"sexo": "Feminino",
		"signo": "Gêmeos",
		"mae": "Alana Clarice Lavínia",
		"pai": "Iago Roberto Caldeira",
		"email": "aanalurebecabeneditacaldeira@pp33.com.br",
		"senha": "MQo7FX7Iz3",
		"cep": "41490516",
		"endereco": "Rua Desembargador Wilde de Lima",
		"numero": 343,
		"bairro": "Mussurunga I",
		"cidade": "Salvador",
		"estado": "BA",
		"telefone_fixo": "7137230941",
		"celular": "71994344283",
		"altura": "1,82",
		"peso": 62,
		"tipo_sanguineo": "O-",
		"cor": "amarelo"
	},
	{
		"nome": "Martin André Benjamin Figueiredo",
		"idade": 72,
		"cpf": "77602120540",
		"rg": "303552074",
		"data_nasc": "27\/07\/1949",
		"sexo": "Masculino",
		"signo": "Leão",
		"mae": "Bianca Camila Maitê",
		"pai": "Luiz Manuel Martin Figueiredo",
		"email": "martinandrebenjaminfigueiredo__martinandrebenjaminfigueiredo@taclog.com.br",
		"senha": "qI0ULFfeKD",
		"cep": "68020720",
		"endereco": "Avenida Tupaiulândia",
		"numero": 494,
		"bairro": "São José Operário",
		"cidade": "Santarém",
		"estado": "PA",
		"telefone_fixo": "9337543370",
		"celular": "93984582330",
		"altura": "1,93",
		"peso": 85,
		"tipo_sanguineo": "B-",
		"cor": "verde"
	},
	{
		"nome": "Olivia Luana Souza",
		"idade": 51,
		"cpf": "12370604603",
		"rg": "415745081",
		"data_nasc": "11\/12\/1970",
		"sexo": "Feminino",
		"signo": "Sagitário",
		"mae": "Rosângela Analu Heloise",
		"pai": "Roberto Rodrigo Matheus Souza",
		"email": "olivialuanasouza_@racml.com.br",
		"senha": "C14Zi6AnYp",
		"cep": "96425600",
		"endereco": "Rua Cândido Portinari",
		"numero": 797,
		"bairro": "Floresta",
		"cidade": "Bagé",
		"estado": "RS",
		"telefone_fixo": "5338276229",
		"celular": "53993757066",
		"altura": "1,82",
		"peso": 52,
		"tipo_sanguineo": "AB+",
		"cor": "azul"
	},
	{
		"nome": "Paulo Benedito Diogo Silveira",
		"idade": 80,
		"cpf": "79054851538",
		"rg": "349784784",
		"data_nasc": "13\/03\/1941",
		"sexo": "Masculino",
		"signo": "Peixes",
		"mae": "Carolina Pietra Isabelly",
		"pai": "Diogo Roberto Miguel Silveira",
		"email": "ppaulobeneditodiogosilveira@sent.com",
		"senha": "EuoJRFC1Ml",
		"cep": "06673540",
		"endereco": "Rua Taboão da Serra",
		"numero": 587,
		"bairro": "Jardim São Marcos",
		"cidade": "Itapevi",
		"estado": "SP",
		"telefone_fixo": "1125187579",
		"celular": "11985624207",
		"altura": "1,69",
		"peso": 98,
		"tipo_sanguineo": "B-",
		"cor": "vermelho"
	},
	{
		"nome": "Carolina Esther Almeida",
		"idade": 75,
		"cpf": "15587007812",
		"rg": "145574829",
		"data_nasc": "11\/10\/1946",
		"sexo": "Feminino",
		"signo": "Libra",
		"mae": "Lúcia Hadassa Sabrina",
		"pai": "Osvaldo Igor Almeida",
		"email": "carolinaestheralmeida_@clcimoveis.com.br",
		"senha": "4cpePbkSOa",
		"cep": "55032574",
		"endereco": "Avenida José Condé",
		"numero": 859,
		"bairro": "Agamenom Magalhães",
		"cidade": "Caruaru",
		"estado": "PE",
		"telefone_fixo": "8136678199",
		"celular": "81997416830",
		"altura": "1,67",
		"peso": 54,
		"tipo_sanguineo": "AB-",
		"cor": "vermelho"
	},
	{
		"nome": "Jennifer Rita Teixeira",
		"idade": 39,
		"cpf": "81932515631",
		"rg": "110573328",
		"data_nasc": "24\/05\/1982",
		"sexo": "Feminino",
		"signo": "Gêmeos",
		"mae": "Brenda Flávia Natália",
		"pai": "Edson Gael Martin Teixeira",
		"email": "jenniferritateixeira__jenniferritateixeira@isbt.com.br",
		"senha": "cUbZpq8zRn",
		"cep": "59050130",
		"endereco": "1ª Rua Santa Helena",
		"numero": 389,
		"bairro": "Quintas",
		"cidade": "Natal",
		"estado": "RN",
		"telefone_fixo": "8435605084",
		"celular": "84995968253",
		"altura": "1,67",
		"peso": 84,
		"tipo_sanguineo": "B-",
		"cor": "vermelho"
	},
	{
		"nome": "Emanuelly Emily Valentina Campos",
		"idade": 36,
		"cpf": "01569712166",
		"rg": "306916101",
		"data_nasc": "17\/05\/1985",
		"sexo": "Feminino",
		"signo": "Touro",
		"mae": "Vitória Liz Sara",
		"pai": "Gabriel Yuri Campos",
		"email": "emanuellyemilyvalentinacampos-86@transporteveloz.com.br",
		"senha": "cSd87ZrGo4",
		"cep": "82700390",
		"endereco": "Rua dos Cedros",
		"numero": 448,
		"bairro": "Barreirinha",
		"cidade": "Curitiba",
		"estado": "PR",
		"telefone_fixo": "4135628022",
		"celular": "41999797823",
		"altura": "1,61",
		"peso": 49,
		"tipo_sanguineo": "O+",
		"cor": "laranja"
	},
	{
		"nome": "Rafaela Julia Nunes",
		"idade": 43,
		"cpf": "91571264612",
		"rg": "137111538",
		"data_nasc": "04\/07\/1978",
		"sexo": "Feminino",
		"signo": "Câncer",
		"mae": "Caroline Amanda",
		"pai": "Yago Vinicius Nunes",
		"email": "rafaelajulianunes..rafaelajulianunes@bravo.com.br",
		"senha": "NoQuYYCBxr",
		"cep": "38701296",
		"endereco": "Rua João Geraldo de Souza",
		"numero": 698,
		"bairro": "Cerrado",
		"cidade": "Patos de Minas",
		"estado": "MG",
		"telefone_fixo": "3438726452",
		"celular": "34983307671",
		"altura": "1,65",
		"peso": 76,
		"tipo_sanguineo": "A-",
		"cor": "preto"
	},
	{
		"nome": "Silvana Rita Tereza Corte Real",
		"idade": 77,
		"cpf": "85516283302",
		"rg": "433860121",
		"data_nasc": "04\/09\/1944",
		"sexo": "Feminino",
		"signo": "Virgem",
		"mae": "Luana Brenda",
		"pai": "Iago Thales Corte Real",
		"email": "silvanaritaterezacortereal__silvanaritaterezacortereal@novotempo.com",
		"senha": "MY8aORwSQY",
		"cep": "68911134",
		"endereco": "Rua Rio Iguaçú",
		"numero": 475,
		"bairro": "Fazendinha",
		"cidade": "Macapá",
		"estado": "AP",
		"telefone_fixo": "9637534748",
		"celular": "96994537723",
		"altura": "1,62",
		"peso": 75,
		"tipo_sanguineo": "O-",
		"cor": "roxo"
	},
	{
		"nome": "Bruna Nina Luiza da Rocha",
		"idade": 57,
		"cpf": "80434206610",
		"rg": "210205805",
		"data_nasc": "21\/12\/1964",
		"sexo": "Feminino",
		"signo": "Sagitário",
		"mae": "Gabrielly Tereza",
		"pai": "Isaac Breno Murilo da Rocha",
		"email": "brunaninaluizadarocha_@sadefem.com.br",
		"senha": "CC6fYUtc7W",
		"cep": "71572602",
		"endereco": "Quadra Quadra 26 Conjunto B",
		"numero": 332,
		"bairro": "Paranoá",
		"cidade": "Brasília",
		"estado": "DF",
		"telefone_fixo": "6137518682",
		"celular": "61999415018",
		"altura": "1,62",
		"peso": 90,
		"tipo_sanguineo": "B-",
		"cor": "vermelho"
	},
	{
		"nome": "Elisa Cláudia Jéssica Moura",
		"idade": 68,
		"cpf": "17532551636",
		"rg": "320661179",
		"data_nasc": "11\/11\/1953",
		"sexo": "Feminino",
		"signo": "Escorpião",
		"mae": "Isis Betina",
		"pai": "Lorenzo Yuri Moura",
		"email": "elisaclaudiajessicamoura-71@focusgrafica.com.br",
		"senha": "UAc3Tqc0zE",
		"cep": "77426026",
		"endereco": "Rua A9",
		"numero": 467,
		"bairro": "Residencial Park dos Buritis",
		"cidade": "Gurupi",
		"estado": "TO",
		"telefone_fixo": "6337321315",
		"celular": "63999539287",
		"altura": "1,67",
		"peso": 80,
		"tipo_sanguineo": "B+",
		"cor": "azul"
	}
]